pynamodb_session_manager/__init__.py
pynamodb_session_manager/_version.py
pynamodb_session_manager/api.py
pynamodb_session_manager/impl.py
pynamodb_session_manager/paths.py
pynamodb_session_manager/vendor/__init__.py
pynamodb_session_manager/vendor/pytest_cov_helper.py
pynamodb_session_manager-0.1.2.dist-info/AUTHORS.rst
pynamodb_session_manager-0.1.2.dist-info/LICENSE.txt
pynamodb_session_manager-0.1.2.dist-info/METADATA
pynamodb_session_manager-0.1.2.dist-info/WHEEL
pynamodb_session_manager-0.1.2.dist-info/RECORD
